diveai/__init__.py
diveai/metrics.py
diveai/models/__init__.py
diveai/models/linear_regression.py
diveai/models/logistic_regression.py
diveai/plotting.py
diveai/visualization.py
diveai-0.1.3.dist-info/METADATA
diveai-0.1.3.dist-info/WHEEL
diveai-0.1.3.dist-info/RECORD
